dooblr/__init__.py
dooblr/_version.py
dooblr/config.py
dooblr/main.py
dooblr/mqttclient.py
dooblr-3.1.0.dist-info/DESCRIPTION.rst
dooblr-3.1.0.dist-info/METADATA
dooblr-3.1.0.dist-info/RECORD
dooblr-3.1.0.dist-info/WHEEL
dooblr-3.1.0.dist-info/entry_points.txt
dooblr-3.1.0.dist-info/metadata.json
dooblr-3.1.0.dist-info/top_level.txt
