Metadata-Version: 2.0
Name: dooblr
Version: 3.1.0
Summary: Duplicate data received over MQTT to InfluxDB
Home-page: https://github.com/makerslocal/dooblr
Author: Tyler Crumpton
Author-email: tyler.crumpton@gmail.com
License: ISC
Platform: UNKNOWN
Classifier: Development Status :: 3 - Alpha
Classifier: Intended Audience :: Developers
Classifier: License :: OSI Approved :: ISC License (ISCL)
Classifier: Operating System :: OS Independent
Classifier: Programming Language :: Python :: 2
Classifier: Programming Language :: Python :: 2.7
Classifier: Programming Language :: Python :: 3
Classifier: Programming Language :: Python :: 3.3
Classifier: Programming Language :: Python :: 3.4
Classifier: Programming Language :: Python :: 3.5
Requires-Dist: configparser
Requires-Dist: influxdb
Requires-Dist: paho-mqtt
Requires-Dist: pyyaml
Requires-Dist: schema
